<?xml version="1.0" encoding="UTF-8"?>
<!DOCTYPE QtCreatorProfiles>
<!-- Written by QtCreator 9.0.1, 2023-02-18T21:35:29. -->
<qtcreator>
 <data>
  <variable>Kit.IrrelevantAspects</variable>
  <valuelist type="QVariantList"/>
 </data>
 <data>
  <variable>Profile.0</variable>
  <valuemap type="QVariantMap">
   <value type="bool" key="PE.Profile.AutoDetected">false</value>
   <value type="QString" key="PE.Profile.AutoDetectionSource"></value>
   <valuemap type="QVariantMap" key="PE.Profile.Data">
    <valuelist type="QVariantList" key="CMake.ConfigurationKitInformation">
     <value type="QString">QT_QMAKE_EXECUTABLE:FILEPATH=%{Qt:qmakeExecutable}</value>
     <value type="QString">CMAKE_PREFIX_PATH:PATH=%{Qt:QT_INSTALL_PREFIX}</value>
     <value type="QString">CMAKE_C_COMPILER:FILEPATH=%{Compiler:Executable:C}</value>
     <value type="QString">CMAKE_CXX_COMPILER:FILEPATH=%{Compiler:Executable:Cxx}</value>
    </valuelist>
    <valuemap type="QVariantMap" key="CMake.GeneratorKitInformation">
     <value type="QString" key="ExtraGenerator"></value>
     <value type="QString" key="Generator">Ninja</value>
     <value type="QString" key="Platform"></value>
     <value type="QString" key="Toolset"></value>
    </valuemap>
    <value type="QString" key="CMakeProjectManager.CMakeKitInformation">{2f922f75-59b9-4bab-bb5f-fcffaf3ea110}</value>
    <value type="QString" key="Debugger.Information">{822a2def-7b39-4867-9cd6-d170a2181228}</value>
    <value type="QString" key="PE.Profile.Device">Desktop Device</value>
    <value type="QString" key="PE.Profile.DeviceType">Desktop</value>
    <valuemap type="QVariantMap" key="PE.Profile.ToolChainsV3">
     <value type="QByteArray" key="C">{84d56cd4-d041-4df3-be62-71cab5eee8c8}</value>
     <value type="QByteArray" key="Cxx">{283cfb41-f06f-44d7-940e-76adb94440ce}</value>
    </valuemap>
    <value type="int" key="QtSupport.QtInformation">3</value>
   </valuemap>
   <value type="QString" key="PE.Profile.DeviceTypeForIcon"></value>
   <value type="QString" key="PE.Profile.Icon"></value>
   <value type="QString" key="PE.Profile.Id">{959dbff3-064a-4709-853e-cc2fba08c8a6}</value>
   <valuelist type="QVariantList" key="PE.Profile.MutableInfo"/>
   <value type="QString" key="PE.Profile.Name">Desktop</value>
   <value type="bool" key="PE.Profile.SDK">false</value>
   <valuelist type="QVariantList" key="PE.Profile.StickyInfo"/>
  </valuemap>
 </data>
 <data>
  <variable>Profile.1</variable>
  <valuemap type="QVariantMap">
   <value type="bool" key="PE.Profile.AutoDetected">false</value>
   <value type="QString" key="PE.Profile.AutoDetectionSource"></value>
   <valuemap type="QVariantMap" key="PE.Profile.Data">
    <value type="QString" key="CMake.AdditionalConfigurationParameters"></value>
    <valuelist type="QVariantList" key="CMake.ConfigurationKitInformation">
     <value type="QString">QT_QMAKE_EXECUTABLE:FILEPATH=%{Qt:qmakeExecutable}</value>
     <value type="QString">CMAKE_PREFIX_PATH:PATH=%{Qt:QT_INSTALL_PREFIX}</value>
     <value type="QString">CMAKE_C_COMPILER:FILEPATH=%{Compiler:Executable:C}</value>
     <value type="QString">CMAKE_CXX_COMPILER:FILEPATH=%{Compiler:Executable:Cxx}</value>
     <value type="QString">QT_HOST_PATH:PATH=%{Qt:QT_HOST_PREFIX}</value>
     <value type="QString">CMAKE_MAKE_PROGRAM:STRING=ninja</value>
     <value type="QString">CMAKE_CXX_FLAGS_INIT:STRING=-DQT_QML_DEBUG</value>
    </valuelist>
    <valuemap type="QVariantMap" key="CMake.GeneratorKitInformation">
     <value type="QString" key="ExtraGenerator"></value>
     <value type="QString" key="Generator">Ninja</value>
     <value type="QString" key="Platform"></value>
     <value type="QString" key="Toolset"></value>
    </valuemap>
    <value type="QString" key="CMakeProjectManager.CMakeKitInformation">{2f922f75-59b9-4bab-bb5f-fcffaf3ea110}</value>
    <value type="QString" key="Debugger.Information">{822a2def-7b39-4867-9cd6-d170a2181228}</value>
    <value type="QString" key="PE.Profile.Device">WebAssembly Device</value>
    <value type="QString" key="PE.Profile.DeviceType">WebAssemblyDeviceType</value>
    <valuemap type="QVariantMap" key="PE.Profile.ToolChainsV3">
     <value type="QByteArray" key="C">{8b015ae8-9277-4fb1-98ed-d67ff1f16598}</value>
     <value type="QByteArray" key="Cxx">{c2d0e014-e2ce-41de-8535-1d9e888d5186}</value>
    </valuemap>
    <value type="int" key="QtSupport.QtInformation">2</value>
   </valuemap>
   <value type="QString" key="PE.Profile.DeviceTypeForIcon"></value>
   <value type="QString" key="PE.Profile.Icon"></value>
   <value type="QString" key="PE.Profile.Id">{90c1e7cb-f51c-4c8e-86ff-85911b14a96d}</value>
   <valuelist type="QVariantList" key="PE.Profile.MutableInfo"/>
   <value type="QString" key="PE.Profile.Name">WebAssembly</value>
   <value type="bool" key="PE.Profile.SDK">false</value>
   <valuelist type="QVariantList" key="PE.Profile.StickyInfo"/>
  </valuemap>
 </data>
 <data>
  <variable>Profile.Count</variable>
  <value type="int">2</value>
 </data>
 <data>
  <variable>Profile.Default</variable>
  <value type="QString">{959dbff3-064a-4709-853e-cc2fba08c8a6}</value>
 </data>
 <data>
  <variable>Version</variable>
  <value type="int">1</value>
 </data>
</qtcreator>
